odoo/addons/mrp_production_byproduct_cost_share/README.rst
odoo/addons/mrp_production_byproduct_cost_share/__init__.py
odoo/addons/mrp_production_byproduct_cost_share/__manifest__.py
odoo/addons/mrp_production_byproduct_cost_share/i18n/es.po
odoo/addons/mrp_production_byproduct_cost_share/i18n/it.po
odoo/addons/mrp_production_byproduct_cost_share/i18n/mrp_production_byproduct_cost_share.pot
odoo/addons/mrp_production_byproduct_cost_share/models/__init__.py
odoo/addons/mrp_production_byproduct_cost_share/models/mrp_bom.py
odoo/addons/mrp_production_byproduct_cost_share/models/mrp_production.py
odoo/addons/mrp_production_byproduct_cost_share/models/product.py
odoo/addons/mrp_production_byproduct_cost_share/models/stock_move.py
odoo/addons/mrp_production_byproduct_cost_share/readme/CONFIGURE.rst
odoo/addons/mrp_production_byproduct_cost_share/readme/CONTRIBUTORS.rst
odoo/addons/mrp_production_byproduct_cost_share/readme/DESCRIPTION.rst
odoo/addons/mrp_production_byproduct_cost_share/readme/HISTORY.rst
odoo/addons/mrp_production_byproduct_cost_share/readme/ROADMAP.rst
odoo/addons/mrp_production_byproduct_cost_share/report/__init__.py
odoo/addons/mrp_production_byproduct_cost_share/report/mrp_report_bom_structure.py
odoo/addons/mrp_production_byproduct_cost_share/report/mrp_report_bom_structure.xml
odoo/addons/mrp_production_byproduct_cost_share/static/description/icon.png
odoo/addons/mrp_production_byproduct_cost_share/static/description/index.html
odoo/addons/mrp_production_byproduct_cost_share/static/src/js/mrp_bom_report.js
odoo/addons/mrp_production_byproduct_cost_share/tests/__init__.py
odoo/addons/mrp_production_byproduct_cost_share/tests/test_mrp_production_byproduct_cost_share.py
odoo/addons/mrp_production_byproduct_cost_share/views/mrp_bom_views.xml
odoo/addons/mrp_production_byproduct_cost_share/views/mrp_production_views.xml
odoo/addons/mrp_production_byproduct_cost_share/views/mrp_template.xml
odoo14_addon_mrp_production_byproduct_cost_share-14.0.1.0.1.dev6.dist-info/METADATA
odoo14_addon_mrp_production_byproduct_cost_share-14.0.1.0.1.dev6.dist-info/WHEEL
odoo14_addon_mrp_production_byproduct_cost_share-14.0.1.0.1.dev6.dist-info/top_level.txt
odoo14_addon_mrp_production_byproduct_cost_share-14.0.1.0.1.dev6.dist-info/RECORD
