Metadata-Version: 2.1
Name: odoo14-addon-mrp-production-byproduct-cost-share
Version: 14.0.1.0.1.dev6
Summary: Production By-Product Cost Share
Home-page: https://github.com/OCA/manufacture
Author: ForgeFlow, Odoo Community Association (OCA), Odoo S.A.
Author-email: support@odoo-community.org
License: LGPL-3
Platform: UNKNOWN
Classifier: Programming Language :: Python
Classifier: Framework :: Odoo
Classifier: Framework :: Odoo :: 14.0
Classifier: License :: OSI Approved :: GNU Lesser General Public License v3 (LGPLv3)
Requires-Python: >=3.6
Requires-Dist: odoo <14.1dev,>=14.0a
